[
  {
    "ContainingType": "SuperShop_Management.Controllers.AdminController",
    "Method": "GetRoles",
    "RelativePath": "api/Admin/roles",
    "HttpMethod": "GET",
    "IsController": true,
    "Order": 0,
    "Parameters": [],
    "ReturnTypes": []
  },
  {
    "ContainingType": "SuperShop_Management.Controllers.AdminController",
    "Method": "CreateRole",
    "RelativePath": "api/Admin/roles",
    "HttpMethod": "POST",
    "IsController": true,
    "Order": 0,
    "Parameters": [
      {
        "Name": "dto",
        "Type": "SuperShop_Management.DTOs.Admin.CreateRoleDto",
        "IsRequired": true
      }
    ],
    "ReturnTypes": []
  },
  {
    "ContainingType": "SuperShop_Management.Controllers.AdminController",
    "Method": "RenameRole",
    "RelativePath": "api/Admin/roles/{roleName}",
    "HttpMethod": "PUT",
    "IsController": true,
    "Order": 0,
    "Parameters": [
      {
        "Name": "roleName",
        "Type": "System.String",
        "IsRequired": true
      },
      {
        "Name": "dto",
        "Type": "SuperShop_Management.DTOs.Admin.UpdateRoleDto",
        "IsRequired": true
      }
    ],
    "ReturnTypes": []
  },
  {
    "ContainingType": "SuperShop_Management.Controllers.AdminController",
    "Method": "DeleteRole",
    "RelativePath": "api/Admin/roles/{roleName}",
    "HttpMethod": "DELETE",
    "IsController": true,
    "Order": 0,
    "Parameters": [
      {
        "Name": "roleName",
        "Type": "System.String",
        "IsRequired": true
      }
    ],
    "ReturnTypes": []
  },
  {
    "ContainingType": "SuperShop_Management.Controllers.AdminController",
    "Method": "GetRolePermissions",
    "RelativePath": "api/Admin/roles/{roleName}/permissions",
    "HttpMethod": "GET",
    "IsController": true,
    "Order": 0,
    "Parameters": [
      {
        "Name": "roleName",
        "Type": "System.String",
        "IsRequired": true
      }
    ],
    "ReturnTypes": []
  },
  {
    "ContainingType": "SuperShop_Management.Controllers.AdminController",
    "Method": "SetRolePermissions",
    "RelativePath": "api/Admin/roles/{roleName}/permissions",
    "HttpMethod": "PUT",
    "IsController": true,
    "Order": 0,
    "Parameters": [
      {
        "Name": "roleName",
        "Type": "System.String",
        "IsRequired": true
      },
      {
        "Name": "dto",
        "Type": "SuperShop_Management.DTOs.Admin.SetRolePermissionsDto",
        "IsRequired": true
      }
    ],
    "ReturnTypes": []
  },
  {
    "ContainingType": "SuperShop_Management.Controllers.AdminController",
    "Method": "GetUsers",
    "RelativePath": "api/Admin/users",
    "HttpMethod": "GET",
    "IsController": true,
    "Order": 0,
    "Parameters": [],
    "ReturnTypes": []
  },
  {
    "ContainingType": "SuperShop_Management.Controllers.AdminController",
    "Method": "SetUserDepartment",
    "RelativePath": "api/Admin/users/{userId}/department",
    "HttpMethod": "PUT",
    "IsController": true,
    "Order": 0,
    "Parameters": [
      {
        "Name": "userId",
        "Type": "System.Int32",
        "IsRequired": true
      },
      {
        "Name": "dto",
        "Type": "SuperShop_Management.DTOs.Admin.SetUserDepartmentDto",
        "IsRequired": true
      }
    ],
    "ReturnTypes": []
  },
  {
    "ContainingType": "SuperShop_Management.Controllers.AdminController",
    "Method": "SetUserRoles",
    "RelativePath": "api/Admin/users/{userId}/roles",
    "HttpMethod": "PUT",
    "IsController": true,
    "Order": 0,
    "Parameters": [
      {
        "Name": "userId",
        "Type": "System.Int32",
        "IsRequired": true
      },
      {
        "Name": "dto",
        "Type": "SuperShop_Management.DTOs.Admin.SetUserRolesDto",
        "IsRequired": true
      }
    ],
    "ReturnTypes": []
  },
  {
    "ContainingType": "SuperShop_Management.Controllers.AuthController",
    "Method": "Login",
    "RelativePath": "api/Auth/login",
    "HttpMethod": "POST",
    "IsController": true,
    "Order": 0,
    "Parameters": [
      {
        "Name": "dto",
        "Type": "SuperShop_Management.DTOs.Auth.LoginDto",
        "IsRequired": true
      }
    ],
    "ReturnTypes": []
  },
  {
    "ContainingType": "SuperShop_Management.Controllers.AuthController",
    "Method": "Logout",
    "RelativePath": "api/Auth/logout",
    "HttpMethod": "POST",
    "IsController": true,
    "Order": 0,
    "Parameters": [],
    "ReturnTypes": []
  },
  {
    "ContainingType": "SuperShop_Management.Controllers.AuthController",
    "Method": "GetCurrentUser",
    "RelativePath": "api/Auth/me",
    "HttpMethod": "GET",
    "IsController": true,
    "Order": 0,
    "Parameters": [],
    "ReturnTypes": []
  },
  {
    "ContainingType": "SuperShop_Management.Controllers.AuthController",
    "Method": "Register",
    "RelativePath": "api/Auth/register",
    "HttpMethod": "POST",
    "IsController": true,
    "Order": 0,
    "Parameters": [
      {
        "Name": "dto",
        "Type": "SuperShop_Management.DTOs.Auth.RegisterDto",
        "IsRequired": true
      }
    ],
    "ReturnTypes": []
  },
  {
    "ContainingType": "SuperShop_Management.Controllers.BatchController",
    "Method": "GetAll",
    "RelativePath": "api/Batch",
    "HttpMethod": "GET",
    "IsController": true,
    "Order": 0,
    "Parameters": [],
    "ReturnTypes": []
  },
  {
    "ContainingType": "SuperShop_Management.Controllers.BatchController",
    "Method": "Create",
    "RelativePath": "api/Batch",
    "HttpMethod": "POST",
    "IsController": true,
    "Order": 0,
    "Parameters": [
      {
        "Name": "dto",
        "Type": "SuperShop_Management.DTOs.Batch.BatchCreateDto",
        "IsRequired": true
      }
    ],
    "ReturnTypes": []
  },
  {
    "ContainingType": "SuperShop_Management.Controllers.BatchController",
    "Method": "GetById",
    "RelativePath": "api/Batch/{id}",
    "HttpMethod": "GET",
    "IsController": true,
    "Order": 0,
    "Parameters": [
      {
        "Name": "id",
        "Type": "System.Int32",
        "IsRequired": true
      }
    ],
    "ReturnTypes": []
  },
  {
    "ContainingType": "SuperShop_Management.Controllers.BatchController",
    "Method": "Update",
    "RelativePath": "api/Batch/{id}",
    "HttpMethod": "PUT",
    "IsController": true,
    "Order": 0,
    "Parameters": [
      {
        "Name": "id",
        "Type": "System.Int32",
        "IsRequired": true
      },
      {
        "Name": "dto",
        "Type": "SuperShop_Management.DTOs.Batch.BatchUpdateDto",
        "IsRequired": true
      }
    ],
    "ReturnTypes": []
  },
  {
    "ContainingType": "SuperShop_Management.Controllers.BatchController",
    "Method": "Delete",
    "RelativePath": "api/Batch/{id}",
    "HttpMethod": "DELETE",
    "IsController": true,
    "Order": 0,
    "Parameters": [
      {
        "Name": "id",
        "Type": "System.Int32",
        "IsRequired": true
      }
    ],
    "ReturnTypes": []
  },
  {
    "ContainingType": "SuperShop_Management.Controllers.BrandController",
    "Method": "GetAll",
    "RelativePath": "api/Brand",
    "HttpMethod": "GET",
    "IsController": true,
    "Order": 0,
    "Parameters": [],
    "ReturnTypes": []
  },
  {
    "ContainingType": "SuperShop_Management.Controllers.BrandController",
    "Method": "Create",
    "RelativePath": "api/Brand",
    "HttpMethod": "POST",
    "IsController": true,
    "Order": 0,
    "Parameters": [
      {
        "Name": "dto",
        "Type": "SuperShop_Management.DTOs.Brand.BrandRequestDto",
        "IsRequired": true
      }
    ],
    "ReturnTypes": []
  },
  {
    "ContainingType": "SuperShop_Management.Controllers.BrandController",
    "Method": "GetById",
    "RelativePath": "api/Brand/{id}",
    "HttpMethod": "GET",
    "IsController": true,
    "Order": 0,
    "Parameters": [
      {
        "Name": "id",
        "Type": "System.Int32",
        "IsRequired": true
      }
    ],
    "ReturnTypes": []
  },
  {
    "ContainingType": "SuperShop_Management.Controllers.BrandController",
    "Method": "Update",
    "RelativePath": "api/Brand/{id}",
    "HttpMethod": "PUT",
    "IsController": true,
    "Order": 0,
    "Parameters": [
      {
        "Name": "id",
        "Type": "System.Int32",
        "IsRequired": true
      },
      {
        "Name": "dto",
        "Type": "SuperShop_Management.DTOs.Brand.BrandRequestDto",
        "IsRequired": true
      }
    ],
    "ReturnTypes": []
  },
  {
    "ContainingType": "SuperShop_Management.Controllers.BrandController",
    "Method": "Delete",
    "RelativePath": "api/Brand/{id}",
    "HttpMethod": "DELETE",
    "IsController": true,
    "Order": 0,
    "Parameters": [
      {
        "Name": "id",
        "Type": "System.Int32",
        "IsRequired": true
      }
    ],
    "ReturnTypes": []
  },
  {
    "ContainingType": "SuperShop_Management.Controllers.BrandController",
    "Method": "GetBySubCategoryId",
    "RelativePath": "api/Brand/bysubcategory/{subCategoryId}",
    "HttpMethod": "GET",
    "IsController": true,
    "Order": 0,
    "Parameters": [
      {
        "Name": "subCategoryId",
        "Type": "System.Int32",
        "IsRequired": true
      }
    ],
    "ReturnTypes": []
  },
  {
    "ContainingType": "SuperShop_Management.Controllers.ComparativeStatementController",
    "Method": "GetAll",
    "RelativePath": "api/ComparativeStatement",
    "HttpMethod": "GET",
    "IsController": true,
    "Order": 0,
    "Parameters": [],
    "ReturnTypes": []
  },
  {
    "ContainingType": "SuperShop_Management.Controllers.ComparativeStatementController",
    "Method": "Create",
    "RelativePath": "api/ComparativeStatement",
    "HttpMethod": "POST",
    "IsController": true,
    "Order": 0,
    "Parameters": [
      {
        "Name": "dto",
        "Type": "SuperShop_Management.DTOs.ComparativeStatement.CSRequestDto",
        "IsRequired": true
      }
    ],
    "ReturnTypes": []
  },
  {
    "ContainingType": "SuperShop_Management.Controllers.ComparativeStatementController",
    "Method": "GetById",
    "RelativePath": "api/ComparativeStatement/{id}",
    "HttpMethod": "GET",
    "IsController": true,
    "Order": 0,
    "Parameters": [
      {
        "Name": "id",
        "Type": "System.Int32",
        "IsRequired": true
      }
    ],
    "ReturnTypes": []
  },
  {
    "ContainingType": "SuperShop_Management.Controllers.ComparativeStatementController",
    "Method": "Delete",
    "RelativePath": "api/ComparativeStatement/{id}",
    "HttpMethod": "DELETE",
    "IsController": true,
    "Order": 0,
    "Parameters": [
      {
        "Name": "id",
        "Type": "System.Int32",
        "IsRequired": true
      }
    ],
    "ReturnTypes": []
  },
  {
    "ContainingType": "SuperShop_Management.Controllers.ComparativeStatementController",
    "Method": "Approve",
    "RelativePath": "api/ComparativeStatement/{id}/approve",
    "HttpMethod": "PUT",
    "IsController": true,
    "Order": 0,
    "Parameters": [
      {
        "Name": "id",
        "Type": "System.Int32",
        "IsRequired": true
      }
    ],
    "ReturnTypes": []
  },
  {
    "ContainingType": "SuperShop_Management.Controllers.ComparativeStatementController",
    "Method": "PrintCS",
    "RelativePath": "api/ComparativeStatement/{id}/print",
    "HttpMethod": "GET",
    "IsController": true,
    "Order": 0,
    "Parameters": [
      {
        "Name": "id",
        "Type": "System.Int32",
        "IsRequired": true
      }
    ],
    "ReturnTypes": []
  },
  {
    "ContainingType": "SuperShop_Management.Controllers.ComparativeStatementController",
    "Method": "MarkReviewed",
    "RelativePath": "api/ComparativeStatement/{id}/review",
    "HttpMethod": "PUT",
    "IsController": true,
    "Order": 0,
    "Parameters": [
      {
        "Name": "id",
        "Type": "System.Int32",
        "IsRequired": true
      }
    ],
    "ReturnTypes": []
  },
  {
    "ContainingType": "SuperShop_Management.Controllers.ComparativeStatementController",
    "Method": "SelectSuppliers",
    "RelativePath": "api/ComparativeStatement/{id}/select-suppliers",
    "HttpMethod": "POST",
    "IsController": true,
    "Order": 0,
    "Parameters": [
      {
        "Name": "id",
        "Type": "System.Int32",
        "IsRequired": true
      },
      {
        "Name": "dto",
        "Type": "SuperShop_Management.DTOs.ComparativeStatement.SelectSuppliersDto",
        "IsRequired": true
      }
    ],
    "ReturnTypes": []
  },
  {
    "ContainingType": "SuperShop_Management.Controllers.CurrencyController",
    "Method": "GetAll",
    "RelativePath": "api/Currency",
    "HttpMethod": "GET",
    "IsController": true,
    "Order": 0,
    "Parameters": [],
    "ReturnTypes": []
  },
  {
    "ContainingType": "SuperShop_Management.Controllers.CurrencyController",
    "Method": "Create",
    "RelativePath": "api/Currency",
    "HttpMethod": "POST",
    "IsController": true,
    "Order": 0,
    "Parameters": [
      {
        "Name": "dto",
        "Type": "SuperShop_Management.DTOs.Currency.CurrencyRequestDto",
        "IsRequired": true
      }
    ],
    "ReturnTypes": []
  },
  {
    "ContainingType": "SuperShop_Management.Controllers.CurrencyController",
    "Method": "GetById",
    "RelativePath": "api/Currency/{id}",
    "HttpMethod": "GET",
    "IsController": true,
    "Order": 0,
    "Parameters": [
      {
        "Name": "id",
        "Type": "System.Int32",
        "IsRequired": true
      }
    ],
    "ReturnTypes": []
  },
  {
    "ContainingType": "SuperShop_Management.Controllers.CurrencyController",
    "Method": "Update",
    "RelativePath": "api/Currency/{id}",
    "HttpMethod": "PUT",
    "IsController": true,
    "Order": 0,
    "Parameters": [
      {
        "Name": "id",
        "Type": "System.Int32",
        "IsRequired": true
      },
      {
        "Name": "dto",
        "Type": "SuperShop_Management.DTOs.Currency.CurrencyRequestDto",
        "IsRequired": true
      }
    ],
    "ReturnTypes": []
  },
  {
    "ContainingType": "SuperShop_Management.Controllers.CurrencyController",
    "Method": "Delete",
    "RelativePath": "api/Currency/{id}",
    "HttpMethod": "DELETE",
    "IsController": true,
    "Order": 0,
    "Parameters": [
      {
        "Name": "id",
        "Type": "System.Int32",
        "IsRequired": true
      }
    ],
    "ReturnTypes": []
  },
  {
    "ContainingType": "SuperShop_Management.Controllers.DashboardController",
    "Method": "GetStats",
    "RelativePath": "api/Dashboard/stats",
    "HttpMethod": "GET",
    "IsController": true,
    "Order": 0,
    "Parameters": [],
    "ReturnTypes": []
  },
  {
    "ContainingType": "SuperShop_Management.Controllers.DepartmentController",
    "Method": "GetAll",
    "RelativePath": "api/Department",
    "HttpMethod": "GET",
    "IsController": true,
    "Order": 0,
    "Parameters": [],
    "ReturnTypes": []
  },
  {
    "ContainingType": "SuperShop_Management.Controllers.DepartmentController",
    "Method": "Create",
    "RelativePath": "api/Department",
    "HttpMethod": "POST",
    "IsController": true,
    "Order": 0,
    "Parameters": [
      {
        "Name": "dto",
        "Type": "SuperShop_Management.DTOs.Department.DepartmentRequestDto",
        "IsRequired": true
      }
    ],
    "ReturnTypes": []
  },
  {
    "ContainingType": "SuperShop_Management.Controllers.DepartmentController",
    "Method": "GetById",
    "RelativePath": "api/Department/{id}",
    "HttpMethod": "GET",
    "IsController": true,
    "Order": 0,
    "Parameters": [
      {
        "Name": "id",
        "Type": "System.Int32",
        "IsRequired": true
      }
    ],
    "ReturnTypes": []
  },
  {
    "ContainingType": "SuperShop_Management.Controllers.DepartmentController",
    "Method": "Update",
    "RelativePath": "api/Department/{id}",
    "HttpMethod": "PUT",
    "IsController": true,
    "Order": 0,
    "Parameters": [
      {
        "Name": "id",
        "Type": "System.Int32",
        "IsRequired": true
      },
      {
        "Name": "dto",
        "Type": "SuperShop_Management.DTOs.Department.DepartmentRequestDto",
        "IsRequired": true
      }
    ],
    "ReturnTypes": []
  },
  {
    "ContainingType": "SuperShop_Management.Controllers.DepartmentController",
    "Method": "Delete",
    "RelativePath": "api/Department/{id}",
    "HttpMethod": "DELETE",
    "IsController": true,
    "Order": 0,
    "Parameters": [
      {
        "Name": "id",
        "Type": "System.Int32",
        "IsRequired": true
      }
    ],
    "ReturnTypes": []
  },
  {
    "ContainingType": "SuperShop_Management.Controllers.GRNController",
    "Method": "GetAll",
    "RelativePath": "api/GRN",
    "HttpMethod": "GET",
    "IsController": true,
    "Order": 0,
    "Parameters": [],
    "ReturnTypes": []
  },
  {
    "ContainingType": "SuperShop_Management.Controllers.GRNController",
    "Method": "Create",
    "RelativePath": "api/GRN",
    "HttpMethod": "POST",
    "IsController": true,
    "Order": 0,
    "Parameters": [
      {
        "Name": "dto",
        "Type": "SuperShop_Management.DTOs.GRN.GRNRequestDto",
        "IsRequired": true
      }
    ],
    "ReturnTypes": []
  },
  {
    "ContainingType": "SuperShop_Management.Controllers.GRNController",
    "Method": "GetById",
    "RelativePath": "api/GRN/{id}",
    "HttpMethod": "GET",
    "IsController": true,
    "Order": 0,
    "Parameters": [
      {
        "Name": "id",
        "Type": "System.Int32",
        "IsRequired": true
      }
    ],
    "ReturnTypes": []
  },
  {
    "ContainingType": "SuperShop_Management.Controllers.GRNController",
    "Method": "Delete",
    "RelativePath": "api/GRN/{id}",
    "HttpMethod": "DELETE",
    "IsController": true,
    "Order": 0,
    "Parameters": [
      {
        "Name": "id",
        "Type": "System.Int32",
        "IsRequired": true
      }
    ],
    "ReturnTypes": []
  },
  {
    "ContainingType": "SuperShop_Management.Controllers.GRNController",
    "Method": "Approve",
    "RelativePath": "api/GRN/{id}/approve",
    "HttpMethod": "PATCH",
    "IsController": true,
    "Order": 0,
    "Parameters": [
      {
        "Name": "id",
        "Type": "System.Int32",
        "IsRequired": true
      },
      {
        "Name": "locationDto",
        "Type": "SuperShop_Management.Controllers.ApproveGRNDto",
        "IsRequired": true
      }
    ],
    "ReturnTypes": []
  },
  {
    "ContainingType": "SuperShop_Management.Controllers.GRNController",
    "Method": "CompleteQC",
    "RelativePath": "api/GRN/{id}/qc-complete",
    "HttpMethod": "PUT",
    "IsController": true,
    "Order": 0,
    "Parameters": [
      {
        "Name": "id",
        "Type": "System.Int32",
        "IsRequired": true
      },
      {
        "Name": "qcUpdates",
        "Type": "System.Collections.Generic.List\u00601[[SuperShop_Management.Controllers.QCUpdateDto, SuperShop_Management, Version=1.0.0.0, Culture=neutral, PublicKeyToken=null]]",
        "IsRequired": true
      }
    ],
    "ReturnTypes": []
  },
  {
    "ContainingType": "SuperShop_Management.Controllers.GRNController",
    "Method": "Reject",
    "RelativePath": "api/GRN/{id}/reject",
    "HttpMethod": "PATCH",
    "IsController": true,
    "Order": 0,
    "Parameters": [
      {
        "Name": "id",
        "Type": "System.Int32",
        "IsRequired": true
      },
      {
        "Name": "dto",
        "Type": "SuperShop_Management.Controllers.RejectGRNDto",
        "IsRequired": true
      }
    ],
    "ReturnTypes": []
  },
  {
    "ContainingType": "SuperShop_Management.Controllers.GRNController",
    "Method": "Submit",
    "RelativePath": "api/GRN/{id}/submit",
    "HttpMethod": "PATCH",
    "IsController": true,
    "Order": 0,
    "Parameters": [
      {
        "Name": "id",
        "Type": "System.Int32",
        "IsRequired": true
      }
    ],
    "ReturnTypes": []
  },
  {
    "ContainingType": "SuperShop_Management.Controllers.GRNController",
    "Method": "DirectReceive",
    "RelativePath": "api/GRN/direct-receive",
    "HttpMethod": "POST",
    "IsController": true,
    "Order": 0,
    "Parameters": [
      {
        "Name": "dto",
        "Type": "SuperShop_Management.DTOs.GRN.DirectReceiveDto",
        "IsRequired": true
      }
    ],
    "ReturnTypes": []
  },
  {
    "ContainingType": "SuperShop_Management.Controllers.InventoryController",
    "Method": "GetAll",
    "RelativePath": "api/Inventory",
    "HttpMethod": "GET",
    "IsController": true,
    "Order": 0,
    "Parameters": [],
    "ReturnTypes": []
  },
  {
    "ContainingType": "SuperShop_Management.Controllers.InventoryController",
    "Method": "GetById",
    "RelativePath": "api/Inventory/{id}",
    "HttpMethod": "GET",
    "IsController": true,
    "Order": 0,
    "Parameters": [
      {
        "Name": "id",
        "Type": "System.Int32",
        "IsRequired": true
      }
    ],
    "ReturnTypes": []
  },
  {
    "ContainingType": "SuperShop_Management.Controllers.InventoryController",
    "Method": "GetByLocation",
    "RelativePath": "api/Inventory/by-location",
    "HttpMethod": "GET",
    "IsController": true,
    "Order": 0,
    "Parameters": [
      {
        "Name": "warehouseId",
        "Type": "System.Nullable\u00601[[System.Int32, System.Private.CoreLib, Version=8.0.0.0, Culture=neutral, PublicKeyToken=7cec85d7bea7798e]]",
        "IsRequired": false
      },
      {
        "Name": "floorId",
        "Type": "System.Nullable\u00601[[System.Int32, System.Private.CoreLib, Version=8.0.0.0, Culture=neutral, PublicKeyToken=7cec85d7bea7798e]]",
        "IsRequired": false
      },
      {
        "Name": "zoneId",
        "Type": "System.Nullable\u00601[[System.Int32, System.Private.CoreLib, Version=8.0.0.0, Culture=neutral, PublicKeyToken=7cec85d7bea7798e]]",
        "IsRequired": false
      },
      {
        "Name": "aisleId",
        "Type": "System.Nullable\u00601[[System.Int32, System.Private.CoreLib, Version=8.0.0.0, Culture=neutral, PublicKeyToken=7cec85d7bea7798e]]",
        "IsRequired": false
      },
      {
        "Name": "rackId",
        "Type": "System.Nullable\u00601[[System.Int32, System.Private.CoreLib, Version=8.0.0.0, Culture=neutral, PublicKeyToken=7cec85d7bea7798e]]",
        "IsRequired": false
      },
      {
        "Name": "shelfId",
        "Type": "System.Nullable\u00601[[System.Int32, System.Private.CoreLib, Version=8.0.0.0, Culture=neutral, PublicKeyToken=7cec85d7bea7798e]]",
        "IsRequired": false
      },
      {
        "Name": "binId",
        "Type": "System.Nullable\u00601[[System.Int32, System.Private.CoreLib, Version=8.0.0.0, Culture=neutral, PublicKeyToken=7cec85d7bea7798e]]",
        "IsRequired": false
      }
    ],
    "ReturnTypes": []
  },
  {
    "ContainingType": "SuperShop_Management.Controllers.InventoryController",
    "Method": "GetByProduct",
    "RelativePath": "api/Inventory/by-product/{productId}",
    "HttpMethod": "GET",
    "IsController": true,
    "Order": 0,
    "Parameters": [
      {
        "Name": "productId",
        "Type": "System.Int32",
        "IsRequired": true
      }
    ],
    "ReturnTypes": []
  },
  {
    "ContainingType": "SuperShop_Management.Controllers.InventoryController",
    "Method": "GetLowStockItems",
    "RelativePath": "api/Inventory/low-stock",
    "HttpMethod": "GET",
    "IsController": true,
    "Order": 0,
    "Parameters": [],
    "ReturnTypes": []
  },
  {
    "ContainingType": "SuperShop_Management.Controllers.ItemCategoryController",
    "Method": "GetAll",
    "RelativePath": "api/ItemCategory",
    "HttpMethod": "GET",
    "IsController": true,
    "Order": 0,
    "Parameters": [],
    "ReturnTypes": []
  },
  {
    "ContainingType": "SuperShop_Management.Controllers.ItemCategoryController",
    "Method": "Create",
    "RelativePath": "api/ItemCategory",
    "HttpMethod": "POST",
    "IsController": true,
    "Order": 0,
    "Parameters": [
      {
        "Name": "dto",
        "Type": "SuperShop_Management.DTOs.ItemCategory.ItemCategoryRequestDto",
        "IsRequired": true
      }
    ],
    "ReturnTypes": []
  },
  {
    "ContainingType": "SuperShop_Management.Controllers.ItemCategoryController",
    "Method": "GetById",
    "RelativePath": "api/ItemCategory/{id}",
    "HttpMethod": "GET",
    "IsController": true,
    "Order": 0,
    "Parameters": [
      {
        "Name": "id",
        "Type": "System.Int32",
        "IsRequired": true
      }
    ],
    "ReturnTypes": []
  },
  {
    "ContainingType": "SuperShop_Management.Controllers.ItemCategoryController",
    "Method": "Update",
    "RelativePath": "api/ItemCategory/{id}",
    "HttpMethod": "PUT",
    "IsController": true,
    "Order": 0,
    "Parameters": [
      {
        "Name": "id",
        "Type": "System.Int32",
        "IsRequired": true
      },
      {
        "Name": "dto",
        "Type": "SuperShop_Management.DTOs.ItemCategory.ItemCategoryRequestDto",
        "IsRequired": true
      }
    ],
    "ReturnTypes": []
  },
  {
    "ContainingType": "SuperShop_Management.Controllers.ItemCategoryController",
    "Method": "Delete",
    "RelativePath": "api/ItemCategory/{id}",
    "HttpMethod": "DELETE",
    "IsController": true,
    "Order": 0,
    "Parameters": [
      {
        "Name": "id",
        "Type": "System.Int32",
        "IsRequired": true
      }
    ],
    "ReturnTypes": []
  },
  {
    "ContainingType": "SuperShop_Management.Controllers.LocationController",
    "Method": "GetAisles",
    "RelativePath": "api/location/aisles",
    "HttpMethod": "GET",
    "IsController": true,
    "Order": 0,
    "Parameters": [],
    "ReturnTypes": []
  },
  {
    "ContainingType": "SuperShop_Management.Controllers.LocationController",
    "Method": "CreateAisle",
    "RelativePath": "api/location/aisles",
    "HttpMethod": "POST",
    "IsController": true,
    "Order": 0,
    "Parameters": [
      {
        "Name": "dto",
        "Type": "SuperShop_Management.DTOs.Location.AisleRequestDto",
        "IsRequired": true
      }
    ],
    "ReturnTypes": []
  },
  {
    "ContainingType": "SuperShop_Management.Controllers.LocationController",
    "Method": "GetAisle",
    "RelativePath": "api/location/aisles/{id}",
    "HttpMethod": "GET",
    "IsController": true,
    "Order": 0,
    "Parameters": [
      {
        "Name": "id",
        "Type": "System.Int32",
        "IsRequired": true
      }
    ],
    "ReturnTypes": []
  },
  {
    "ContainingType": "SuperShop_Management.Controllers.LocationController",
    "Method": "UpdateAisle",
    "RelativePath": "api/location/aisles/{id}",
    "HttpMethod": "PUT",
    "IsController": true,
    "Order": 0,
    "Parameters": [
      {
        "Name": "id",
        "Type": "System.Int32",
        "IsRequired": true
      },
      {
        "Name": "dto",
        "Type": "SuperShop_Management.DTOs.Location.AisleRequestDto",
        "IsRequired": true
      }
    ],
    "ReturnTypes": []
  },
  {
    "ContainingType": "SuperShop_Management.Controllers.LocationController",
    "Method": "DeleteAisle",
    "RelativePath": "api/location/aisles/{id}",
    "HttpMethod": "DELETE",
    "IsController": true,
    "Order": 0,
    "Parameters": [
      {
        "Name": "id",
        "Type": "System.Int32",
        "IsRequired": true
      }
    ],
    "ReturnTypes": []
  },
  {
    "ContainingType": "SuperShop_Management.Controllers.LocationController",
    "Method": "GetAislesByZone",
    "RelativePath": "api/location/aisles/by-zone/{zoneId}",
    "HttpMethod": "GET",
    "IsController": true,
    "Order": 0,
    "Parameters": [
      {
        "Name": "zoneId",
        "Type": "System.Int32",
        "IsRequired": true
      }
    ],
    "ReturnTypes": []
  },
  {
    "ContainingType": "SuperShop_Management.Controllers.LocationController",
    "Method": "GetBins",
    "RelativePath": "api/location/bins",
    "HttpMethod": "GET",
    "IsController": true,
    "Order": 0,
    "Parameters": [],
    "ReturnTypes": []
  },
  {
    "ContainingType": "SuperShop_Management.Controllers.LocationController",
    "Method": "CreateBin",
    "RelativePath": "api/location/bins",
    "HttpMethod": "POST",
    "IsController": true,
    "Order": 0,
    "Parameters": [
      {
        "Name": "dto",
        "Type": "SuperShop_Management.DTOs.Location.BinRequestDto",
        "IsRequired": true
      }
    ],
    "ReturnTypes": []
  },
  {
    "ContainingType": "SuperShop_Management.Controllers.LocationController",
    "Method": "GetBin",
    "RelativePath": "api/location/bins/{id}",
    "HttpMethod": "GET",
    "IsController": true,
    "Order": 0,
    "Parameters": [
      {
        "Name": "id",
        "Type": "System.Int32",
        "IsRequired": true
      }
    ],
    "ReturnTypes": []
  },
  {
    "ContainingType": "SuperShop_Management.Controllers.LocationController",
    "Method": "UpdateBin",
    "RelativePath": "api/location/bins/{id}",
    "HttpMethod": "PUT",
    "IsController": true,
    "Order": 0,
    "Parameters": [
      {
        "Name": "id",
        "Type": "System.Int32",
        "IsRequired": true
      },
      {
        "Name": "dto",
        "Type": "SuperShop_Management.DTOs.Location.BinRequestDto",
        "IsRequired": true
      }
    ],
    "ReturnTypes": []
  },
  {
    "ContainingType": "SuperShop_Management.Controllers.LocationController",
    "Method": "DeleteBin",
    "RelativePath": "api/location/bins/{id}",
    "HttpMethod": "DELETE",
    "IsController": true,
    "Order": 0,
    "Parameters": [
      {
        "Name": "id",
        "Type": "System.Int32",
        "IsRequired": true
      }
    ],
    "ReturnTypes": []
  },
  {
    "ContainingType": "SuperShop_Management.Controllers.LocationController",
    "Method": "GetBinsByShelf",
    "RelativePath": "api/location/bins/by-shelf/{shelfId}",
    "HttpMethod": "GET",
    "IsController": true,
    "Order": 0,
    "Parameters": [
      {
        "Name": "shelfId",
        "Type": "System.Int32",
        "IsRequired": true
      }
    ],
    "ReturnTypes": []
  },
  {
    "ContainingType": "SuperShop_Management.Controllers.LocationController",
    "Method": "GetDropdowns",
    "RelativePath": "api/location/dropdowns",
    "HttpMethod": "GET",
    "IsController": true,
    "Order": 0,
    "Parameters": [
      {
        "Name": "warehouseId",
        "Type": "System.Nullable\u00601[[System.Int32, System.Private.CoreLib, Version=8.0.0.0, Culture=neutral, PublicKeyToken=7cec85d7bea7798e]]",
        "IsRequired": false
      },
      {
        "Name": "floorId",
        "Type": "System.Nullable\u00601[[System.Int32, System.Private.CoreLib, Version=8.0.0.0, Culture=neutral, PublicKeyToken=7cec85d7bea7798e]]",
        "IsRequired": false
      },
      {
        "Name": "zoneId",
        "Type": "System.Nullable\u00601[[System.Int32, System.Private.CoreLib, Version=8.0.0.0, Culture=neutral, PublicKeyToken=7cec85d7bea7798e]]",
        "IsRequired": false
      },
      {
        "Name": "aisleId",
        "Type": "System.Nullable\u00601[[System.Int32, System.Private.CoreLib, Version=8.0.0.0, Culture=neutral, PublicKeyToken=7cec85d7bea7798e]]",
        "IsRequired": false
      },
      {
        "Name": "rackId",
        "Type": "System.Nullable\u00601[[System.Int32, System.Private.CoreLib, Version=8.0.0.0, Culture=neutral, PublicKeyToken=7cec85d7bea7798e]]",
        "IsRequired": false
      },
      {
        "Name": "shelfId",
        "Type": "System.Nullable\u00601[[System.Int32, System.Private.CoreLib, Version=8.0.0.0, Culture=neutral, PublicKeyToken=7cec85d7bea7798e]]",
        "IsRequired": false
      }
    ],
    "ReturnTypes": []
  },
  {
    "ContainingType": "SuperShop_Management.Controllers.LocationController",
    "Method": "GetFloors",
    "RelativePath": "api/location/floors",
    "HttpMethod": "GET",
    "IsController": true,
    "Order": 0,
    "Parameters": [],
    "ReturnTypes": []
  },
  {
    "ContainingType": "SuperShop_Management.Controllers.LocationController",
    "Method": "CreateFloor",
    "RelativePath": "api/location/floors",
    "HttpMethod": "POST",
    "IsController": true,
    "Order": 0,
    "Parameters": [
      {
        "Name": "dto",
        "Type": "SuperShop_Management.DTOs.Location.FloorRequestDto",
        "IsRequired": true
      }
    ],
    "ReturnTypes": []
  },
  {
    "ContainingType": "SuperShop_Management.Controllers.LocationController",
    "Method": "GetFloor",
    "RelativePath": "api/location/floors/{id}",
    "HttpMethod": "GET",
    "IsController": true,
    "Order": 0,
    "Parameters": [
      {
        "Name": "id",
        "Type": "System.Int32",
        "IsRequired": true
      }
    ],
    "ReturnTypes": []
  },
  {
    "ContainingType": "SuperShop_Management.Controllers.LocationController",
    "Method": "UpdateFloor",
    "RelativePath": "api/location/floors/{id}",
    "HttpMethod": "PUT",
    "IsController": true,
    "Order": 0,
    "Parameters": [
      {
        "Name": "id",
        "Type": "System.Int32",
        "IsRequired": true
      },
      {
        "Name": "dto",
        "Type": "SuperShop_Management.DTOs.Location.FloorRequestDto",
        "IsRequired": true
      }
    ],
    "ReturnTypes": []
  },
  {
    "ContainingType": "SuperShop_Management.Controllers.LocationController",
    "Method": "DeleteFloor",
    "RelativePath": "api/location/floors/{id}",
    "HttpMethod": "DELETE",
    "IsController": true,
    "Order": 0,
    "Parameters": [
      {
        "Name": "id",
        "Type": "System.Int32",
        "IsRequired": true
      }
    ],
    "ReturnTypes": []
  },
  {
    "ContainingType": "SuperShop_Management.Controllers.LocationController",
    "Method": "GetFloorsByWarehouse",
    "RelativePath": "api/location/floors/by-warehouse/{warehouseId}",
    "HttpMethod": "GET",
    "IsController": true,
    "Order": 0,
    "Parameters": [
      {
        "Name": "warehouseId",
        "Type": "System.Int32",
        "IsRequired": true
      }
    ],
    "ReturnTypes": []
  },
  {
    "ContainingType": "SuperShop_Management.Controllers.LocationController",
    "Method": "GetIndex",
    "RelativePath": "api/location/index",
    "HttpMethod": "GET",
    "IsController": true,
    "Order": 0,
    "Parameters": [],
    "ReturnTypes": []
  },
  {
    "ContainingType": "SuperShop_Management.Controllers.LocationController",
    "Method": "GetRacks",
    "RelativePath": "api/location/racks",
    "HttpMethod": "GET",
    "IsController": true,
    "Order": 0,
    "Parameters": [],
    "ReturnTypes": []
  },
  {
    "ContainingType": "SuperShop_Management.Controllers.LocationController",
    "Method": "CreateRack",
    "RelativePath": "api/location/racks",
    "HttpMethod": "POST",
    "IsController": true,
    "Order": 0,
    "Parameters": [
      {
        "Name": "dto",
        "Type": "SuperShop_Management.DTOs.Location.RackRequestDto",
        "IsRequired": true
      }
    ],
    "ReturnTypes": []
  },
  {
    "ContainingType": "SuperShop_Management.Controllers.LocationController",
    "Method": "GetRack",
    "RelativePath": "api/location/racks/{id}",
    "HttpMethod": "GET",
    "IsController": true,
    "Order": 0,
    "Parameters": [
      {
        "Name": "id",
        "Type": "System.Int32",
        "IsRequired": true
      }
    ],
    "ReturnTypes": []
  },
  {
    "ContainingType": "SuperShop_Management.Controllers.LocationController",
    "Method": "UpdateRack",
    "RelativePath": "api/location/racks/{id}",
    "HttpMethod": "PUT",
    "IsController": true,
    "Order": 0,
    "Parameters": [
      {
        "Name": "id",
        "Type": "System.Int32",
        "IsRequired": true
      },
      {
        "Name": "dto",
        "Type": "SuperShop_Management.DTOs.Location.RackRequestDto",
        "IsRequired": true
      }
    ],
    "ReturnTypes": []
  },
  {
    "ContainingType": "SuperShop_Management.Controllers.LocationController",
    "Method": "DeleteRack",
    "RelativePath": "api/location/racks/{id}",
    "HttpMethod": "DELETE",
    "IsController": true,
    "Order": 0,
    "Parameters": [
      {
        "Name": "id",
        "Type": "System.Int32",
        "IsRequired": true
      }
    ],
    "ReturnTypes": []
  },
  {
    "ContainingType": "SuperShop_Management.Controllers.LocationController",
    "Method": "GetRacksByAisle",
    "RelativePath": "api/location/racks/by-aisle/{aisleId}",
    "HttpMethod": "GET",
    "IsController": true,
    "Order": 0,
    "Parameters": [
      {
        "Name": "aisleId",
        "Type": "System.Int32",
        "IsRequired": true
      }
    ],
    "ReturnTypes": []
  },
  {
    "ContainingType": "SuperShop_Management.Controllers.LocationController",
    "Method": "GetShelfs",
    "RelativePath": "api/location/shelfs",
    "HttpMethod": "GET",
    "IsController": true,
    "Order": 0,
    "Parameters": [],
    "ReturnTypes": []
  },
  {
    "ContainingType": "SuperShop_Management.Controllers.LocationController",
    "Method": "CreateShelf",
    "RelativePath": "api/location/shelfs",
    "HttpMethod": "POST",
    "IsController": true,
    "Order": 0,
    "Parameters": [
      {
        "Name": "dto",
        "Type": "SuperShop_Management.DTOs.Location.ShelfRequestDto",
        "IsRequired": true
      }
    ],
    "ReturnTypes": []
  },
  {
    "ContainingType": "SuperShop_Management.Controllers.LocationController",
    "Method": "GetShelf",
    "RelativePath": "api/location/shelfs/{id}",
    "HttpMethod": "GET",
    "IsController": true,
    "Order": 0,
    "Parameters": [
      {
        "Name": "id",
        "Type": "System.Int32",
        "IsRequired": true
      }
    ],
    "ReturnTypes": []
  },
  {
    "ContainingType": "SuperShop_Management.Controllers.LocationController",
    "Method": "UpdateShelf",
    "RelativePath": "api/location/shelfs/{id}",
    "HttpMethod": "PUT",
    "IsController": true,
    "Order": 0,
    "Parameters": [
      {
        "Name": "id",
        "Type": "System.Int32",
        "IsRequired": true
      },
      {
        "Name": "dto",
        "Type": "SuperShop_Management.DTOs.Location.ShelfRequestDto",
        "IsRequired": true
      }
    ],
    "ReturnTypes": []
  },
  {
    "ContainingType": "SuperShop_Management.Controllers.LocationController",
    "Method": "DeleteShelf",
    "RelativePath": "api/location/shelfs/{id}",
    "HttpMethod": "DELETE",
    "IsController": true,
    "Order": 0,
    "Parameters": [
      {
        "Name": "id",
        "Type": "System.Int32",
        "IsRequired": true
      }
    ],
    "ReturnTypes": []
  },
  {
    "ContainingType": "SuperShop_Management.Controllers.LocationController",
    "Method": "GetShelfsByRack",
    "RelativePath": "api/location/shelfs/by-rack/{rackId}",
    "HttpMethod": "GET",
    "IsController": true,
    "Order": 0,
    "Parameters": [
      {
        "Name": "rackId",
        "Type": "System.Int32",
        "IsRequired": true
      }
    ],
    "ReturnTypes": []
  },
  {
    "ContainingType": "SuperShop_Management.Controllers.LocationController",
    "Method": "GetTree",
    "RelativePath": "api/location/tree",
    "HttpMethod": "GET",
    "IsController": true,
    "Order": 0,
    "Parameters": [],
    "ReturnTypes": []
  },
  {
    "ContainingType": "SuperShop_Management.Controllers.LocationController",
    "Method": "GetWarehouses",
    "RelativePath": "api/location/warehouses",
    "HttpMethod": "GET",
    "IsController": true,
    "Order": 0,
    "Parameters": [],
    "ReturnTypes": []
  },
  {
    "ContainingType": "SuperShop_Management.Controllers.LocationController",
    "Method": "CreateWarehouse",
    "RelativePath": "api/location/warehouses",
    "HttpMethod": "POST",
    "IsController": true,
    "Order": 0,
    "Parameters": [
      {
        "Name": "dto",
        "Type": "SuperShop_Management.DTOs.Location.WarehouseRequestDto",
        "IsRequired": true
      }
    ],
    "ReturnTypes": []
  },
  {
    "ContainingType": "SuperShop_Management.Controllers.LocationController",
    "Method": "GetWarehouse",
    "RelativePath": "api/location/warehouses/{id}",
    "HttpMethod": "GET",
    "IsController": true,
    "Order": 0,
    "Parameters": [
      {
        "Name": "id",
        "Type": "System.Int32",
        "IsRequired": true
      }
    ],
    "ReturnTypes": []
  },
  {
    "ContainingType": "SuperShop_Management.Controllers.LocationController",
    "Method": "UpdateWarehouse",
    "RelativePath": "api/location/warehouses/{id}",
    "HttpMethod": "PUT",
    "IsController": true,
    "Order": 0,
    "Parameters": [
      {
        "Name": "id",
        "Type": "System.Int32",
        "IsRequired": true
      },
      {
        "Name": "dto",
        "Type": "SuperShop_Management.DTOs.Location.WarehouseRequestDto",
        "IsRequired": true
      }
    ],
    "ReturnTypes": []
  },
  {
    "ContainingType": "SuperShop_Management.Controllers.LocationController",
    "Method": "DeleteWarehouse",
    "RelativePath": "api/location/warehouses/{id}",
    "HttpMethod": "DELETE",
    "IsController": true,
    "Order": 0,
    "Parameters": [
      {
        "Name": "id",
        "Type": "System.Int32",
        "IsRequired": true
      }
    ],
    "ReturnTypes": []
  },
  {
    "ContainingType": "SuperShop_Management.Controllers.LocationController",
    "Method": "GetZones",
    "RelativePath": "api/location/zones",
    "HttpMethod": "GET",
    "IsController": true,
    "Order": 0,
    "Parameters": [],
    "ReturnTypes": []
  },
  {
    "ContainingType": "SuperShop_Management.Controllers.LocationController",
    "Method": "CreateZone",
    "RelativePath": "api/location/zones",
    "HttpMethod": "POST",
    "IsController": true,
    "Order": 0,
    "Parameters": [
      {
        "Name": "dto",
        "Type": "SuperShop_Management.DTOs.Location.ZoneRequestDto",
        "IsRequired": true
      }
    ],
    "ReturnTypes": []
  },
  {
    "ContainingType": "SuperShop_Management.Controllers.LocationController",
    "Method": "GetZone",
    "RelativePath": "api/location/zones/{id}",
    "HttpMethod": "GET",
    "IsController": true,
    "Order": 0,
    "Parameters": [
      {
        "Name": "id",
        "Type": "System.Int32",
        "IsRequired": true
      }
    ],
    "ReturnTypes": []
  },
  {
    "ContainingType": "SuperShop_Management.Controllers.LocationController",
    "Method": "UpdateZone",
    "RelativePath": "api/location/zones/{id}",
    "HttpMethod": "PUT",
    "IsController": true,
    "Order": 0,
    "Parameters": [
      {
        "Name": "id",
        "Type": "System.Int32",
        "IsRequired": true
      },
      {
        "Name": "dto",
        "Type": "SuperShop_Management.DTOs.Location.ZoneRequestDto",
        "IsRequired": true
      }
    ],
    "ReturnTypes": []
  },
  {
    "ContainingType": "SuperShop_Management.Controllers.LocationController",
    "Method": "DeleteZone",
    "RelativePath": "api/location/zones/{id}",
    "HttpMethod": "DELETE",
    "IsController": true,
    "Order": 0,
    "Parameters": [
      {
        "Name": "id",
        "Type": "System.Int32",
        "IsRequired": true
      }
    ],
    "ReturnTypes": []
  },
  {
    "ContainingType": "SuperShop_Management.Controllers.LocationController",
    "Method": "GetZonesByFloor",
    "RelativePath": "api/location/zones/by-floor/{floorId}",
    "HttpMethod": "GET",
    "IsController": true,
    "Order": 0,
    "Parameters": [
      {
        "Name": "floorId",
        "Type": "System.Int32",
        "IsRequired": true
      }
    ],
    "ReturnTypes": []
  },
  {
    "ContainingType": "SuperShop_Management.Controllers.ProductController",
    "Method": "GetAll",
    "RelativePath": "api/Product",
    "HttpMethod": "GET",
    "IsController": true,
    "Order": 0,
    "Parameters": [],
    "ReturnTypes": []
  },
  {
    "ContainingType": "SuperShop_Management.Controllers.ProductController",
    "Method": "Create",
    "RelativePath": "api/Product",
    "HttpMethod": "POST",
    "IsController": true,
    "Order": 0,
    "Parameters": [
      {
        "Name": "dto",
        "Type": "SuperShop_Management.DTOs.Product.ProductRequestDto",
        "IsRequired": true
      }
    ],
    "ReturnTypes": []
  },
  {
    "ContainingType": "SuperShop_Management.Controllers.ProductController",
    "Method": "GetById",
    "RelativePath": "api/Product/{id}",
    "HttpMethod": "GET",
    "IsController": true,
    "Order": 0,
    "Parameters": [
      {
        "Name": "id",
        "Type": "System.Int32",
        "IsRequired": true
      }
    ],
    "ReturnTypes": []
  },
  {
    "ContainingType": "SuperShop_Management.Controllers.ProductController",
    "Method": "Update",
    "RelativePath": "api/Product/{id}",
    "HttpMethod": "PUT",
    "IsController": true,
    "Order": 0,
    "Parameters": [
      {
        "Name": "id",
        "Type": "System.Int32",
        "IsRequired": true
      },
      {
        "Name": "dto",
        "Type": "SuperShop_Management.DTOs.Product.ProductRequestDto",
        "IsRequired": true
      }
    ],
    "ReturnTypes": []
  },
  {
    "ContainingType": "SuperShop_Management.Controllers.ProductController",
    "Method": "Delete",
    "RelativePath": "api/Product/{id}",
    "HttpMethod": "DELETE",
    "IsController": true,
    "Order": 0,
    "Parameters": [
      {
        "Name": "id",
        "Type": "System.Int32",
        "IsRequired": true
      }
    ],
    "ReturnTypes": []
  },
  {
    "ContainingType": "SuperShop_Management.Controllers.ProductController",
    "Method": "GetByBarcode",
    "RelativePath": "api/Product/barcode/{barcode}",
    "HttpMethod": "GET",
    "IsController": true,
    "Order": 0,
    "Parameters": [
      {
        "Name": "barcode",
        "Type": "System.String",
        "IsRequired": true
      }
    ],
    "ReturnTypes": []
  },
  {
    "ContainingType": "SuperShop_Management.Controllers.ProductController",
    "Method": "GetByBrandId",
    "RelativePath": "api/Product/bybrand/{brandId}",
    "HttpMethod": "GET",
    "IsController": true,
    "Order": 0,
    "Parameters": [
      {
        "Name": "brandId",
        "Type": "System.Int32",
        "IsRequired": true
      }
    ],
    "ReturnTypes": []
  },
  {
    "ContainingType": "SuperShop_Management.Controllers.ProductController",
    "Method": "GetByCategoryId",
    "RelativePath": "api/Product/bycategory/{categoryId}",
    "HttpMethod": "GET",
    "IsController": true,
    "Order": 0,
    "Parameters": [
      {
        "Name": "categoryId",
        "Type": "System.Int32",
        "IsRequired": true
      }
    ],
    "ReturnTypes": []
  },
  {
    "ContainingType": "SuperShop_Management.Controllers.PurchaseOrderController",
    "Method": "GetAll",
    "RelativePath": "api/PurchaseOrder",
    "HttpMethod": "GET",
    "IsController": true,
    "Order": 0,
    "Parameters": [],
    "ReturnTypes": []
  },
  {
    "ContainingType": "SuperShop_Management.Controllers.PurchaseOrderController",
    "Method": "Create",
    "RelativePath": "api/PurchaseOrder",
    "HttpMethod": "POST",
    "IsController": true,
    "Order": 0,
    "Parameters": [
      {
        "Name": "dto",
        "Type": "SuperShop_Management.DTOs.PurchaseOrder.PurchaseOrderRequestDto",
        "IsRequired": true
      }
    ],
    "ReturnTypes": []
  },
  {
    "ContainingType": "SuperShop_Management.Controllers.PurchaseOrderController",
    "Method": "GetById",
    "RelativePath": "api/PurchaseOrder/{id}",
    "HttpMethod": "GET",
    "IsController": true,
    "Order": 0,
    "Parameters": [
      {
        "Name": "id",
        "Type": "System.Int32",
        "IsRequired": true
      }
    ],
    "ReturnTypes": []
  },
  {
    "ContainingType": "SuperShop_Management.Controllers.PurchaseOrderController",
    "Method": "Delete",
    "RelativePath": "api/PurchaseOrder/{id}",
    "HttpMethod": "DELETE",
    "IsController": true,
    "Order": 0,
    "Parameters": [
      {
        "Name": "id",
        "Type": "System.Int32",
        "IsRequired": true
      }
    ],
    "ReturnTypes": []
  },
  {
    "ContainingType": "SuperShop_Management.Controllers.PurchaseOrderController",
    "Method": "Approve",
    "RelativePath": "api/PurchaseOrder/{id}/approve",
    "HttpMethod": "PUT",
    "IsController": true,
    "Order": 0,
    "Parameters": [
      {
        "Name": "id",
        "Type": "System.Int32",
        "IsRequired": true
      }
    ],
    "ReturnTypes": []
  },
  {
    "ContainingType": "SuperShop_Management.Controllers.PurchaseOrderController",
    "Method": "Cancel",
    "RelativePath": "api/PurchaseOrder/{id}/cancel",
    "HttpMethod": "PUT",
    "IsController": true,
    "Order": 0,
    "Parameters": [
      {
        "Name": "id",
        "Type": "System.Int32",
        "IsRequired": true
      }
    ],
    "ReturnTypes": []
  },
  {
    "ContainingType": "SuperShop_Management.Controllers.PurchaseOrderController",
    "Method": "PrintPO",
    "RelativePath": "api/PurchaseOrder/{id}/print",
    "HttpMethod": "GET",
    "IsController": true,
    "Order": 0,
    "Parameters": [
      {
        "Name": "id",
        "Type": "System.Int32",
        "IsRequired": true
      }
    ],
    "ReturnTypes": []
  },
  {
    "ContainingType": "SuperShop_Management.Controllers.PurchaseOrderController",
    "Method": "Reject",
    "RelativePath": "api/PurchaseOrder/{id}/reject",
    "HttpMethod": "PUT",
    "IsController": true,
    "Order": 0,
    "Parameters": [
      {
        "Name": "id",
        "Type": "System.Int32",
        "IsRequired": true
      },
      {
        "Name": "dto",
        "Type": "SuperShop_Management.Controllers.RejectPODto",
        "IsRequired": true
      }
    ],
    "ReturnTypes": []
  },
  {
    "ContainingType": "SuperShop_Management.Controllers.PurchaseOrderController",
    "Method": "SendToSupplier",
    "RelativePath": "api/PurchaseOrder/{id}/send",
    "HttpMethod": "PUT",
    "IsController": true,
    "Order": 0,
    "Parameters": [
      {
        "Name": "id",
        "Type": "System.Int32",
        "IsRequired": true
      }
    ],
    "ReturnTypes": []
  },
  {
    "ContainingType": "SuperShop_Management.Controllers.PurchaseOrderController",
    "Method": "SubmitForApproval",
    "RelativePath": "api/PurchaseOrder/{id}/submit",
    "HttpMethod": "PUT",
    "IsController": true,
    "Order": 0,
    "Parameters": [
      {
        "Name": "id",
        "Type": "System.Int32",
        "IsRequired": true
      }
    ],
    "ReturnTypes": []
  },
  {
    "ContainingType": "SuperShop_Management.Controllers.PurchaseOrderController",
    "Method": "GetFromCS",
    "RelativePath": "api/PurchaseOrder/FromCS/{csId}",
    "HttpMethod": "GET",
    "IsController": true,
    "Order": 0,
    "Parameters": [
      {
        "Name": "csId",
        "Type": "System.Int32",
        "IsRequired": true
      }
    ],
    "ReturnTypes": []
  },
  {
    "ContainingType": "SuperShop_Management.Controllers.PurchaseRequisitionController",
    "Method": "GetAll",
    "RelativePath": "api/PurchaseRequisition",
    "HttpMethod": "GET",
    "IsController": true,
    "Order": 0,
    "Parameters": [],
    "ReturnTypes": []
  },
  {
    "ContainingType": "SuperShop_Management.Controllers.PurchaseRequisitionController",
    "Method": "Create",
    "RelativePath": "api/PurchaseRequisition",
    "HttpMethod": "POST",
    "IsController": true,
    "Order": 0,
    "Parameters": [
      {
        "Name": "dto",
        "Type": "SuperShop_Management.DTOs.PurchaseRequisition.RequisitionRequestDto",
        "IsRequired": true
      }
    ],
    "ReturnTypes": []
  },
  {
    "ContainingType": "SuperShop_Management.Controllers.PurchaseRequisitionController",
    "Method": "GetById",
    "RelativePath": "api/PurchaseRequisition/{id}",
    "HttpMethod": "GET",
    "IsController": true,
    "Order": 0,
    "Parameters": [
      {
        "Name": "id",
        "Type": "System.Int32",
        "IsRequired": true
      }
    ],
    "ReturnTypes": []
  },
  {
    "ContainingType": "SuperShop_Management.Controllers.PurchaseRequisitionController",
    "Method": "Update",
    "RelativePath": "api/PurchaseRequisition/{id}",
    "HttpMethod": "PUT",
    "IsController": true,
    "Order": 0,
    "Parameters": [
      {
        "Name": "id",
        "Type": "System.Int32",
        "IsRequired": true
      },
      {
        "Name": "dto",
        "Type": "SuperShop_Management.DTOs.PurchaseRequisition.RequisitionRequestDto",
        "IsRequired": true
      }
    ],
    "ReturnTypes": []
  },
  {
    "ContainingType": "SuperShop_Management.Controllers.PurchaseRequisitionController",
    "Method": "Delete",
    "RelativePath": "api/PurchaseRequisition/{id}",
    "HttpMethod": "DELETE",
    "IsController": true,
    "Order": 0,
    "Parameters": [
      {
        "Name": "id",
        "Type": "System.Int32",
        "IsRequired": true
      }
    ],
    "ReturnTypes": []
  },
  {
    "ContainingType": "SuperShop_Management.Controllers.PurchaseRequisitionController",
    "Method": "Approve",
    "RelativePath": "api/PurchaseRequisition/{id}/approve",
    "HttpMethod": "PUT",
    "IsController": true,
    "Order": 0,
    "Parameters": [
      {
        "Name": "id",
        "Type": "System.Int32",
        "IsRequired": true
      }
    ],
    "ReturnTypes": []
  },
  {
    "ContainingType": "SuperShop_Management.Controllers.PurchaseRequisitionController",
    "Method": "GetItemsByRequisitionId",
    "RelativePath": "api/PurchaseRequisition/{id}/items",
    "HttpMethod": "GET",
    "IsController": true,
    "Order": 0,
    "Parameters": [
      {
        "Name": "id",
        "Type": "System.Int32",
        "IsRequired": true
      }
    ],
    "ReturnTypes": []
  },
  {
    "ContainingType": "SuperShop_Management.Controllers.PurchaseRequisitionController",
    "Method": "Reject",
    "RelativePath": "api/PurchaseRequisition/{id}/reject",
    "HttpMethod": "PUT",
    "IsController": true,
    "Order": 0,
    "Parameters": [
      {
        "Name": "id",
        "Type": "System.Int32",
        "IsRequired": true
      },
      {
        "Name": "dto",
        "Type": "SuperShop_Management.DTOs.PurchaseRequisition.RejectReasonDto",
        "IsRequired": false
      }
    ],
    "ReturnTypes": []
  },
  {
    "ContainingType": "SuperShop_Management.Controllers.PurchaseRequisitionController",
    "Method": "GetRequisitionStatus",
    "RelativePath": "api/PurchaseRequisition/{id}/status",
    "HttpMethod": "GET",
    "IsController": true,
    "Order": 0,
    "Parameters": [
      {
        "Name": "id",
        "Type": "System.Int32",
        "IsRequired": true
      }
    ],
    "ReturnTypes": []
  },
  {
    "ContainingType": "SuperShop_Management.Controllers.PurchaseRequisitionController",
    "Method": "GetRequisitionsForApproval",
    "RelativePath": "api/PurchaseRequisition/for-approval",
    "HttpMethod": "GET",
    "IsController": true,
    "Order": 0,
    "Parameters": [],
    "ReturnTypes": []
  },
  {
    "ContainingType": "SuperShop_Management.Controllers.PurchaseRequisitionController",
    "Method": "GetMyDepartmentPendingRequisitions",
    "RelativePath": "api/PurchaseRequisition/my-department-pending",
    "HttpMethod": "GET",
    "IsController": true,
    "Order": 0,
    "Parameters": [],
    "ReturnTypes": []
  },
  {
    "ContainingType": "SuperShop_Management.Controllers.PurchaseRequisitionController",
    "Method": "GetMyRequisitions",
    "RelativePath": "api/PurchaseRequisition/my-requisitions",
    "HttpMethod": "GET",
    "IsController": true,
    "Order": 0,
    "Parameters": [],
    "ReturnTypes": []
  },
  {
    "ContainingType": "SuperShop_Management.Controllers.PurchaseRequisitionController",
    "Method": "GetPendingRequisitions",
    "RelativePath": "api/PurchaseRequisition/pending",
    "HttpMethod": "GET",
    "IsController": true,
    "Order": 0,
    "Parameters": [],
    "ReturnTypes": []
  },
  {
    "ContainingType": "SuperShop_Management.Controllers.QualityCheckController",
    "Method": "GetAll",
    "RelativePath": "api/QualityCheck",
    "HttpMethod": "GET",
    "IsController": true,
    "Order": 0,
    "Parameters": [],
    "ReturnTypes": []
  },
  {
    "ContainingType": "SuperShop_Management.Controllers.QualityCheckController",
    "Method": "Create",
    "RelativePath": "api/QualityCheck",
    "HttpMethod": "POST",
    "IsController": true,
    "Order": 0,
    "Parameters": [
      {
        "Name": "dto",
        "Type": "SuperShop_Management.DTOs.QualityCheck.QCCreateDto",
        "IsRequired": true
      }
    ],
    "ReturnTypes": []
  },
  {
    "ContainingType": "SuperShop_Management.Controllers.QualityCheckController",
    "Method": "GetById",
    "RelativePath": "api/QualityCheck/{id}",
    "HttpMethod": "GET",
    "IsController": true,
    "Order": 0,
    "Parameters": [
      {
        "Name": "id",
        "Type": "System.Int32",
        "IsRequired": true
      }
    ],
    "ReturnTypes": []
  },
  {
    "ContainingType": "SuperShop_Management.Controllers.QualityCheckController",
    "Method": "Delete",
    "RelativePath": "api/QualityCheck/{id}",
    "HttpMethod": "DELETE",
    "IsController": true,
    "Order": 0,
    "Parameters": [
      {
        "Name": "id",
        "Type": "System.Int32",
        "IsRequired": true
      }
    ],
    "ReturnTypes": []
  },
  {
    "ContainingType": "SuperShop_Management.Controllers.QualityCheckController",
    "Method": "GetByGRNId",
    "RelativePath": "api/QualityCheck/bygrn/{grnId}",
    "HttpMethod": "GET",
    "IsController": true,
    "Order": 0,
    "Parameters": [
      {
        "Name": "grnId",
        "Type": "System.Int32",
        "IsRequired": true
      }
    ],
    "ReturnTypes": []
  },
  {
    "ContainingType": "SuperShop_Management.Controllers.RequestForQuotationController",
    "Method": "GetAll",
    "RelativePath": "api/RequestForQuotation",
    "HttpMethod": "GET",
    "IsController": true,
    "Order": 0,
    "Parameters": [],
    "ReturnTypes": []
  },
  {
    "ContainingType": "SuperShop_Management.Controllers.RequestForQuotationController",
    "Method": "Create",
    "RelativePath": "api/RequestForQuotation",
    "HttpMethod": "POST",
    "IsController": true,
    "Order": 0,
    "Parameters": [
      {
        "Name": "dto",
        "Type": "SuperShop_Management.DTOs.RequestForQuotation.RFQRequestDto",
        "IsRequired": true
      }
    ],
    "ReturnTypes": []
  },
  {
    "ContainingType": "SuperShop_Management.Controllers.RequestForQuotationController",
    "Method": "GetById",
    "RelativePath": "api/RequestForQuotation/{id}",
    "HttpMethod": "GET",
    "IsController": true,
    "Order": 0,
    "Parameters": [
      {
        "Name": "id",
        "Type": "System.Int32",
        "IsRequired": true
      }
    ],
    "ReturnTypes": []
  },
  {
    "ContainingType": "SuperShop_Management.Controllers.RequestForQuotationController",
    "Method": "Delete",
    "RelativePath": "api/RequestForQuotation/{id}",
    "HttpMethod": "DELETE",
    "IsController": true,
    "Order": 0,
    "Parameters": [
      {
        "Name": "id",
        "Type": "System.Int32",
        "IsRequired": true
      }
    ],
    "ReturnTypes": []
  },
  {
    "ContainingType": "SuperShop_Management.Controllers.RequestForQuotationController",
    "Method": "Close",
    "RelativePath": "api/RequestForQuotation/{id}/close",
    "HttpMethod": "PUT",
    "IsController": true,
    "Order": 0,
    "Parameters": [
      {
        "Name": "id",
        "Type": "System.Int32",
        "IsRequired": true
      }
    ],
    "ReturnTypes": []
  },
  {
    "ContainingType": "SuperShop_Management.Controllers.RequestForQuotationController",
    "Method": "PrintRFQ",
    "RelativePath": "api/RequestForQuotation/{id}/print",
    "HttpMethod": "GET",
    "IsController": true,
    "Order": 0,
    "Parameters": [
      {
        "Name": "id",
        "Type": "System.Int32",
        "IsRequired": true
      }
    ],
    "ReturnTypes": []
  },
  {
    "ContainingType": "SuperShop_Management.Controllers.RequestForQuotationController",
    "Method": "SendToSuppliers",
    "RelativePath": "api/RequestForQuotation/{id}/send",
    "HttpMethod": "POST",
    "IsController": true,
    "Order": 0,
    "Parameters": [
      {
        "Name": "id",
        "Type": "System.Int32",
        "IsRequired": true
      },
      {
        "Name": "dto",
        "Type": "SuperShop_Management.DTOs.RequestForQuotation.SendRFQDto",
        "IsRequired": true
      }
    ],
    "ReturnTypes": []
  },
  {
    "ContainingType": "SuperShop_Management.Controllers.EmployeeRequisitionController",
    "Method": "Create",
    "RelativePath": "api/requisitions",
    "HttpMethod": "POST",
    "IsController": true,
    "Order": 0,
    "Parameters": [
      {
        "Name": "dto",
        "Type": "SuperShop_Management.DTOs.EmployeeRequisition.EmployeeRequisitionRequestDto",
        "IsRequired": true
      }
    ],
    "ReturnTypes": []
  },
  {
    "ContainingType": "SuperShop_Management.Controllers.EmployeeRequisitionController",
    "Method": "GetAll",
    "RelativePath": "api/requisitions",
    "HttpMethod": "GET",
    "IsController": true,
    "Order": 0,
    "Parameters": [],
    "ReturnTypes": []
  },
  {
    "ContainingType": "SuperShop_Management.Controllers.EmployeeRequisitionController",
    "Method": "GetById",
    "RelativePath": "api/requisitions/{id}",
    "HttpMethod": "GET",
    "IsController": true,
    "Order": 0,
    "Parameters": [
      {
        "Name": "id",
        "Type": "System.Int32",
        "IsRequired": true
      }
    ],
    "ReturnTypes": []
  },
  {
    "ContainingType": "SuperShop_Management.Controllers.EmployeeRequisitionController",
    "Method": "Delete",
    "RelativePath": "api/requisitions/{id}",
    "HttpMethod": "DELETE",
    "IsController": true,
    "Order": 0,
    "Parameters": [
      {
        "Name": "id",
        "Type": "System.Int32",
        "IsRequired": true
      }
    ],
    "ReturnTypes": []
  },
  {
    "ContainingType": "SuperShop_Management.Controllers.EmployeeRequisitionController",
    "Method": "Approve",
    "RelativePath": "api/requisitions/{id}/approve",
    "HttpMethod": "PATCH",
    "IsController": true,
    "Order": 0,
    "Parameters": [
      {
        "Name": "id",
        "Type": "System.Int32",
        "IsRequired": true
      }
    ],
    "ReturnTypes": []
  },
  {
    "ContainingType": "SuperShop_Management.Controllers.EmployeeRequisitionController",
    "Method": "Revise",
    "RelativePath": "api/requisitions/{id}/revise",
    "HttpMethod": "PATCH",
    "IsController": true,
    "Order": 0,
    "Parameters": [
      {
        "Name": "id",
        "Type": "System.Int32",
        "IsRequired": true
      },
      {
        "Name": "dto",
        "Type": "SuperShop_Management.DTOs.EmployeeRequisition.EmployeeRequisitionReviseDto",
        "IsRequired": true
      }
    ],
    "ReturnTypes": []
  },
  {
    "ContainingType": "SuperShop_Management.Controllers.EmployeeRequisitionController",
    "Method": "Submit",
    "RelativePath": "api/requisitions/{id}/submit",
    "HttpMethod": "PATCH",
    "IsController": true,
    "Order": 0,
    "Parameters": [
      {
        "Name": "id",
        "Type": "System.Int32",
        "IsRequired": true
      }
    ],
    "ReturnTypes": []
  },
  {
    "ContainingType": "SuperShop_Management.Controllers.EmployeeRequisitionController",
    "Method": "UpdateRevised",
    "RelativePath": "api/requisitions/{id}/update-revised",
    "HttpMethod": "PATCH",
    "IsController": true,
    "Order": 0,
    "Parameters": [
      {
        "Name": "id",
        "Type": "System.Int32",
        "IsRequired": true
      },
      {
        "Name": "dto",
        "Type": "SuperShop_Management.DTOs.EmployeeRequisition.EmployeeRequisitionReviseDto",
        "IsRequired": true
      }
    ],
    "ReturnTypes": []
  },
  {
    "ContainingType": "SuperShop_Management.Controllers.EmployeeRequisitionController",
    "Method": "GetMyRequisitions",
    "RelativePath": "api/requisitions/my",
    "HttpMethod": "GET",
    "IsController": true,
    "Order": 0,
    "Parameters": [],
    "ReturnTypes": []
  },
  {
    "ContainingType": "SuperShop_Management.Controllers.StockMovementController",
    "Method": "Create",
    "RelativePath": "api/StockMovement",
    "HttpMethod": "POST",
    "IsController": true,
    "Order": 0,
    "Parameters": [
      {
        "Name": "dto",
        "Type": "SuperShop_Management.DTOs.StockMovement.CreateStockMovementDto",
        "IsRequired": true
      }
    ],
    "ReturnTypes": []
  },
  {
    "ContainingType": "SuperShop_Management.Controllers.StockMovementController",
    "Method": "GetByInventoryId",
    "RelativePath": "api/StockMovement/by-inventory/{inventoryId}",
    "HttpMethod": "GET",
    "IsController": true,
    "Order": 0,
    "Parameters": [
      {
        "Name": "inventoryId",
        "Type": "System.Int32",
        "IsRequired": true
      }
    ],
    "ReturnTypes": []
  },
  {
    "ContainingType": "SuperShop_Management.Controllers.StoreIssueController",
    "Method": "CheckStock",
    "RelativePath": "api/store/check-stock/{productId}",
    "HttpMethod": "GET",
    "IsController": true,
    "Order": 0,
    "Parameters": [
      {
        "Name": "productId",
        "Type": "System.Int32",
        "IsRequired": true
      }
    ],
    "ReturnTypes": []
  },
  {
    "ContainingType": "SuperShop_Management.Controllers.StoreIssueController",
    "Method": "ForwardToPurchase",
    "RelativePath": "api/store/forward-to-purchase",
    "HttpMethod": "POST",
    "IsController": true,
    "Order": 0,
    "Parameters": [
      {
        "Name": "dto",
        "Type": "SuperShop_Management.DTOs.StoreIssue.ForwardToPurchaseDto",
        "IsRequired": true
      }
    ],
    "ReturnTypes": []
  },
  {
    "ContainingType": "SuperShop_Management.Controllers.StoreIssueController",
    "Method": "IssueProduct",
    "RelativePath": "api/store/issue",
    "HttpMethod": "POST",
    "IsController": true,
    "Order": 0,
    "Parameters": [
      {
        "Name": "dto",
        "Type": "SuperShop_Management.DTOs.StoreIssue.StoreIssueRequestDto",
        "IsRequired": true
      }
    ],
    "ReturnTypes": []
  },
  {
    "ContainingType": "SuperShop_Management.Controllers.StoreIssueController",
    "Method": "GetAllIssues",
    "RelativePath": "api/store/issues",
    "HttpMethod": "GET",
    "IsController": true,
    "Order": 0,
    "Parameters": [],
    "ReturnTypes": []
  },
  {
    "ContainingType": "SuperShop_Management.Controllers.StoreIssueController",
    "Method": "GetIssueById",
    "RelativePath": "api/store/issues/{id}",
    "HttpMethod": "GET",
    "IsController": true,
    "Order": 0,
    "Parameters": [
      {
        "Name": "id",
        "Type": "System.Int32",
        "IsRequired": true
      }
    ],
    "ReturnTypes": []
  },
  {
    "ContainingType": "SuperShop_Management.Controllers.StoreIssueController",
    "Method": "GetIssuesByRequisition",
    "RelativePath": "api/store/issues/by-requisition/{requisitionId}",
    "HttpMethod": "GET",
    "IsController": true,
    "Order": 0,
    "Parameters": [
      {
        "Name": "requisitionId",
        "Type": "System.Int32",
        "IsRequired": true
      }
    ],
    "ReturnTypes": []
  },
  {
    "ContainingType": "SuperShop_Management.Controllers.StoreIssueController",
    "Method": "GetPendingRequisitions",
    "RelativePath": "api/store/pending-requisitions",
    "HttpMethod": "GET",
    "IsController": true,
    "Order": 0,
    "Parameters": [],
    "ReturnTypes": []
  },
  {
    "ContainingType": "SuperShop_Management.Controllers.StoreIssueController",
    "Method": "GetPendingRequisitionById",
    "RelativePath": "api/store/pending-requisitions/{id}",
    "HttpMethod": "GET",
    "IsController": true,
    "Order": 0,
    "Parameters": [
      {
        "Name": "id",
        "Type": "System.Int32",
        "IsRequired": true
      }
    ],
    "ReturnTypes": []
  },
  {
    "ContainingType": "SuperShop_Management.Controllers.StoreController",
    "Method": "GetApprovedRequisitions",
    "RelativePath": "api/store/requisitions",
    "HttpMethod": "GET",
    "IsController": true,
    "Order": 0,
    "Parameters": [],
    "ReturnTypes": []
  },
  {
    "ContainingType": "SuperShop_Management.Controllers.SubCategoryController",
    "Method": "GetAll",
    "RelativePath": "api/SubCategory",
    "HttpMethod": "GET",
    "IsController": true,
    "Order": 0,
    "Parameters": [],
    "ReturnTypes": []
  },
  {
    "ContainingType": "SuperShop_Management.Controllers.SubCategoryController",
    "Method": "Create",
    "RelativePath": "api/SubCategory",
    "HttpMethod": "POST",
    "IsController": true,
    "Order": 0,
    "Parameters": [
      {
        "Name": "dto",
        "Type": "SuperShop_Management.DTOs.SubCategory.SubCategoryRequestDto",
        "IsRequired": true
      }
    ],
    "ReturnTypes": []
  },
  {
    "ContainingType": "SuperShop_Management.Controllers.SubCategoryController",
    "Method": "GetById",
    "RelativePath": "api/SubCategory/{id}",
    "HttpMethod": "GET",
    "IsController": true,
    "Order": 0,
    "Parameters": [
      {
        "Name": "id",
        "Type": "System.Int32",
        "IsRequired": true
      }
    ],
    "ReturnTypes": []
  },
  {
    "ContainingType": "SuperShop_Management.Controllers.SubCategoryController",
    "Method": "Update",
    "RelativePath": "api/SubCategory/{id}",
    "HttpMethod": "PUT",
    "IsController": true,
    "Order": 0,
    "Parameters": [
      {
        "Name": "id",
        "Type": "System.Int32",
        "IsRequired": true
      },
      {
        "Name": "dto",
        "Type": "SuperShop_Management.DTOs.SubCategory.SubCategoryRequestDto",
        "IsRequired": true
      }
    ],
    "ReturnTypes": []
  },
  {
    "ContainingType": "SuperShop_Management.Controllers.SubCategoryController",
    "Method": "Delete",
    "RelativePath": "api/SubCategory/{id}",
    "HttpMethod": "DELETE",
    "IsController": true,
    "Order": 0,
    "Parameters": [
      {
        "Name": "id",
        "Type": "System.Int32",
        "IsRequired": true
      }
    ],
    "ReturnTypes": []
  },
  {
    "ContainingType": "SuperShop_Management.Controllers.SubCategoryController",
    "Method": "GetByCategoryId",
    "RelativePath": "api/SubCategory/bycategory/{categoryId}",
    "HttpMethod": "GET",
    "IsController": true,
    "Order": 0,
    "Parameters": [
      {
        "Name": "categoryId",
        "Type": "System.Int32",
        "IsRequired": true
      }
    ],
    "ReturnTypes": []
  },
  {
    "ContainingType": "SuperShop_Management.Controllers.SupplierController",
    "Method": "GetAll",
    "RelativePath": "api/Supplier",
    "HttpMethod": "GET",
    "IsController": true,
    "Order": 0,
    "Parameters": [],
    "ReturnTypes": []
  },
  {
    "ContainingType": "SuperShop_Management.Controllers.SupplierController",
    "Method": "Create",
    "RelativePath": "api/Supplier",
    "HttpMethod": "POST",
    "IsController": true,
    "Order": 0,
    "Parameters": [
      {
        "Name": "dto",
        "Type": "SuperShop_Management.DTOs.Supplier.SupplierRequestDto",
        "IsRequired": true
      }
    ],
    "ReturnTypes": []
  },
  {
    "ContainingType": "SuperShop_Management.Controllers.SupplierController",
    "Method": "GetById",
    "RelativePath": "api/Supplier/{id}",
    "HttpMethod": "GET",
    "IsController": true,
    "Order": 0,
    "Parameters": [
      {
        "Name": "id",
        "Type": "System.Int32",
        "IsRequired": true
      }
    ],
    "ReturnTypes": []
  },
  {
    "ContainingType": "SuperShop_Management.Controllers.SupplierController",
    "Method": "Update",
    "RelativePath": "api/Supplier/{id}",
    "HttpMethod": "PUT",
    "IsController": true,
    "Order": 0,
    "Parameters": [
      {
        "Name": "id",
        "Type": "System.Int32",
        "IsRequired": true
      },
      {
        "Name": "dto",
        "Type": "SuperShop_Management.DTOs.Supplier.SupplierRequestDto",
        "IsRequired": true
      }
    ],
    "ReturnTypes": []
  },
  {
    "ContainingType": "SuperShop_Management.Controllers.SupplierController",
    "Method": "Delete",
    "RelativePath": "api/Supplier/{id}",
    "HttpMethod": "DELETE",
    "IsController": true,
    "Order": 0,
    "Parameters": [
      {
        "Name": "id",
        "Type": "System.Int32",
        "IsRequired": true
      }
    ],
    "ReturnTypes": []
  },
  {
    "ContainingType": "SuperShop_Management.Controllers.SupplierQuotationController",
    "Method": "GetAll",
    "RelativePath": "api/SupplierQuotation",
    "HttpMethod": "GET",
    "IsController": true,
    "Order": 0,
    "Parameters": [],
    "ReturnTypes": []
  },
  {
    "ContainingType": "SuperShop_Management.Controllers.SupplierQuotationController",
    "Method": "Create",
    "RelativePath": "api/SupplierQuotation",
    "HttpMethod": "POST",
    "IsController": true,
    "Order": 0,
    "Parameters": [
      {
        "Name": "dto",
        "Type": "SuperShop_Management.DTOs.SupplierQuotation.SupplierQuotationRequestDto",
        "IsRequired": true
      }
    ],
    "ReturnTypes": []
  },
  {
    "ContainingType": "SuperShop_Management.Controllers.SupplierQuotationController",
    "Method": "GetById",
    "RelativePath": "api/SupplierQuotation/{id}",
    "HttpMethod": "GET",
    "IsController": true,
    "Order": 0,
    "Parameters": [
      {
        "Name": "id",
        "Type": "System.Int32",
        "IsRequired": true
      }
    ],
    "ReturnTypes": []
  },
  {
    "ContainingType": "SuperShop_Management.Controllers.SupplierQuotationController",
    "Method": "Delete",
    "RelativePath": "api/SupplierQuotation/{id}",
    "HttpMethod": "DELETE",
    "IsController": true,
    "Order": 0,
    "Parameters": [
      {
        "Name": "id",
        "Type": "System.Int32",
        "IsRequired": true
      }
    ],
    "ReturnTypes": []
  },
  {
    "ContainingType": "SuperShop_Management.Controllers.SupplierQuotationController",
    "Method": "SelectQuotation",
    "RelativePath": "api/SupplierQuotation/{id}/select",
    "HttpMethod": "PUT",
    "IsController": true,
    "Order": 0,
    "Parameters": [
      {
        "Name": "id",
        "Type": "System.Int32",
        "IsRequired": true
      }
    ],
    "ReturnTypes": []
  },
  {
    "ContainingType": "SuperShop_Management.Controllers.SupplierQuotationController",
    "Method": "UpdateStatus",
    "RelativePath": "api/SupplierQuotation/{id}/status",
    "HttpMethod": "PATCH",
    "IsController": true,
    "Order": 0,
    "Parameters": [
      {
        "Name": "id",
        "Type": "System.Int32",
        "IsRequired": true
      },
      {
        "Name": "dto",
        "Type": "SuperShop_Management.Controllers.UpdateQuotationStatusDto",
        "IsRequired": true
      }
    ],
    "ReturnTypes": []
  },
  {
    "ContainingType": "SuperShop_Management.Controllers.SupplierQuotationController",
    "Method": "GetByRFQId",
    "RelativePath": "api/SupplierQuotation/byrfq/{rfqId}",
    "HttpMethod": "GET",
    "IsController": true,
    "Order": 0,
    "Parameters": [
      {
        "Name": "rfqId",
        "Type": "System.Int32",
        "IsRequired": true
      }
    ],
    "ReturnTypes": []
  },
  {
    "ContainingType": "SuperShop_Management.Controllers.UnitController",
    "Method": "GetAll",
    "RelativePath": "api/Unit",
    "HttpMethod": "GET",
    "IsController": true,
    "Order": 0,
    "Parameters": [],
    "ReturnTypes": []
  },
  {
    "ContainingType": "SuperShop_Management.Controllers.UnitController",
    "Method": "Create",
    "RelativePath": "api/Unit",
    "HttpMethod": "POST",
    "IsController": true,
    "Order": 0,
    "Parameters": [
      {
        "Name": "dto",
        "Type": "SuperShop_Management.DTOs.Unit.UnitRequestDto",
        "IsRequired": true
      }
    ],
    "ReturnTypes": []
  },
  {
    "ContainingType": "SuperShop_Management.Controllers.UnitController",
    "Method": "GetById",
    "RelativePath": "api/Unit/{id}",
    "HttpMethod": "GET",
    "IsController": true,
    "Order": 0,
    "Parameters": [
      {
        "Name": "id",
        "Type": "System.Int32",
        "IsRequired": true
      }
    ],
    "ReturnTypes": []
  },
  {
    "ContainingType": "SuperShop_Management.Controllers.UnitController",
    "Method": "Update",
    "RelativePath": "api/Unit/{id}",
    "HttpMethod": "PUT",
    "IsController": true,
    "Order": 0,
    "Parameters": [
      {
        "Name": "id",
        "Type": "System.Int32",
        "IsRequired": true
      },
      {
        "Name": "dto",
        "Type": "SuperShop_Management.DTOs.Unit.UnitRequestDto",
        "IsRequired": true
      }
    ],
    "ReturnTypes": []
  },
  {
    "ContainingType": "SuperShop_Management.Controllers.UnitController",
    "Method": "Delete",
    "RelativePath": "api/Unit/{id}",
    "HttpMethod": "DELETE",
    "IsController": true,
    "Order": 0,
    "Parameters": [
      {
        "Name": "id",
        "Type": "System.Int32",
        "IsRequired": true
      }
    ],
    "ReturnTypes": []
  },
  {
    "ContainingType": "SuperShop_Management.Controllers.UnitController",
    "Method": "GetByUnitSetId",
    "RelativePath": "api/Unit/byset/{unitSetId}",
    "HttpMethod": "GET",
    "IsController": true,
    "Order": 0,
    "Parameters": [
      {
        "Name": "unitSetId",
        "Type": "System.Int32",
        "IsRequired": true
      }
    ],
    "ReturnTypes": []
  },
  {
    "ContainingType": "SuperShop_Management.Controllers.UnitSetController",
    "Method": "GetAll",
    "RelativePath": "api/UnitSet",
    "HttpMethod": "GET",
    "IsController": true,
    "Order": 0,
    "Parameters": [],
    "ReturnTypes": []
  },
  {
    "ContainingType": "SuperShop_Management.Controllers.UnitSetController",
    "Method": "Create",
    "RelativePath": "api/UnitSet",
    "HttpMethod": "POST",
    "IsController": true,
    "Order": 0,
    "Parameters": [
      {
        "Name": "dto",
        "Type": "SuperShop_Management.DTOs.UnitSet.UnitSetRequestDto",
        "IsRequired": true
      }
    ],
    "ReturnTypes": []
  },
  {
    "ContainingType": "SuperShop_Management.Controllers.UnitSetController",
    "Method": "GetById",
    "RelativePath": "api/UnitSet/{id}",
    "HttpMethod": "GET",
    "IsController": true,
    "Order": 0,
    "Parameters": [
      {
        "Name": "id",
        "Type": "System.Int32",
        "IsRequired": true
      }
    ],
    "ReturnTypes": []
  },
  {
    "ContainingType": "SuperShop_Management.Controllers.UnitSetController",
    "Method": "Update",
    "RelativePath": "api/UnitSet/{id}",
    "HttpMethod": "PUT",
    "IsController": true,
    "Order": 0,
    "Parameters": [
      {
        "Name": "id",
        "Type": "System.Int32",
        "IsRequired": true
      },
      {
        "Name": "dto",
        "Type": "SuperShop_Management.DTOs.UnitSet.UnitSetRequestDto",
        "IsRequired": true
      }
    ],
    "ReturnTypes": []
  },
  {
    "ContainingType": "SuperShop_Management.Controllers.UnitSetController",
    "Method": "Delete",
    "RelativePath": "api/UnitSet/{id}",
    "HttpMethod": "DELETE",
    "IsController": true,
    "Order": 0,
    "Parameters": [
      {
        "Name": "id",
        "Type": "System.Int32",
        "IsRequired": true
      }
    ],
    "ReturnTypes": []
  }
]